{
  "project_info": {
    "project_number": "8731362877",
    "firebase_url": "https://voteapp-76567.firebaseio.com",
    "project_id": "voteapp-76567",
    "storage_bucket": "voteapp-76567.appspot.com"
  },
  "client": [
    {
      "client_info": {
        "mobilesdk_app_id": "1:8731362877:android:88fd479830ce7e0e3bcc54",
        "android_client_info": {
          "package_name": "com.android.online.voteapp"
        }
      },
      "oauth_client": [
        {
          "client_id": "8731362877-4m5tusjii9gb5o8p38ne2114i7ekum6o.apps.googleusercontent.com",
          "client_type": 3
        }
      ],
      "api_key": [
        {
          "current_key": "AIzaSyA7zIeRXSyMCMGWdpfcHXQVNjizatdT4wI"
        }
      ],
      "services": {
        "appinvite_service": {
          "other_platform_oauth_client": [
            {
              "client_id": "8731362877-4m5tusjii9gb5o8p38ne2114i7ekum6o.apps.googleusercontent.com",
              "client_type": 3
            }
          ]
        }
      }
    }
  ],
  "configuration_version": "1"
}